EmotionEngine/EmEngine.py
EmotionEngine/EmKeyboardManager.py
EmotionEngine/EmWindowManager.py
EmotionEngine/__init__.py
EmotionEngine/collisions/AABB.py
EmotionEngine/collisions/__init__.py
EmotionEngine/entity/EmEntitiesFactory.py
EmotionEngine/entity/EmEntitiesManager.py
EmotionEngine/entity/EmEntity.py
EmotionEngine/entity/EmEntityHelper.py
EmotionEngine/entity/__init__.py
EmotionEngine/sound/EmSound.py
EmotionEngine/sound/EmSoundsManager.py
EmotionEngine/sound/__init__.py
EmotionEngine/text/EmFontsManager.py
EmotionEngine/text/__init__.py
EmotionEngine/types/EmVector2.py
EmotionEngine/types/__init__.py
EmotionEngine/utils/EmAlternator.py
EmotionEngine/utils/EmTimer.py
EmotionEngine/utils/__init__.py
EmotionEngine/utils/drawing.py
EmotionEngine-1.0.dist-info/LICENSE
EmotionEngine-1.0.dist-info/METADATA
EmotionEngine-1.0.dist-info/WHEEL
EmotionEngine-1.0.dist-info/top_level.txt
EmotionEngine-1.0.dist-info/RECORD
