Metadata-Version: 2.1
Name: EmotionEngine
Version: 1.0
Summary: Toy Playground Engine
Home-page: UNKNOWN
Author: Kevin STOETZEL
Author-email: kevin.stoetzel@gmail.com
License: UNKNOWN
Platform: UNKNOWN
License-File: LICENSE
Requires-Dist: pygame
Requires-Dist: PyYAML
